{
    "creator": "Akrios",
    "description": "\"{bIn the depths of summers yorn,\n steel is pressed, flesh is torn,\n of highest might darkness is born{x\"\n     - Unknown\n\n{r.___________. .___.     {Y.... {r.___________. ._________. ._________. ._________.{x \n{r|           | |   |    {Y/<{W*{Y<  {r|           | |         | |         | |         |{x\n{r|   .___.   | |   |   {Y/>{W*{Y<   {r|   .___.   | | _.   ._ | |  .__.   | |    .___ |{x\n{r|   |   |   | |   |  {Y/>{W*{Y<    {r|   |   |   | '{RV{r |   | {RV{r' |  |  |   | |    |   {RV{r'{x\n{Y}\\  {r|   |   | |   | {Y/>{W*{Y<{D_____{r|   |{D___{r|{D__{r/{D_____{r|   |{D____{r|{D__{r|{D__{r|   |{D_{r|{D____{r|{D____{x  \n{Y}|\\{y-----{r|   |{y------{Y[{Go{Y]       {r|   |            |   |          |   |           {D\\{x\n{Y-{WO{Y->{g\\\\\\\\{r|   |{g\\\\\\\\\\\\\\\\{Y{{R@{Y}{W:::>={r|   |{W============{r|   |{W=========={r|   |{W============{D>{x\n{Y}|/{y-----{r|   |{y------{Y[{Go{Y]{D_______{r|   |{D____________{r|   |{D__________{r|   |{D___________/{x\n{Y}/  {r|   |   | |   | {Y\\>{W*{Y<     {r|   |\\   \\       |   |    |  |  |   |      |    |{x \n{r|   |   |   | |   |  {Y\\>{W*{Y<    {r|   | \\   \\   .__|   |__. |  |__|   | .____|    |{x\n{r|   |   |   | |   |   {Y\\>{W*{Y<   {r|   |  \\   \\  |         | |         | |         |{x\n{r|   |   |   | |   |    {Y\\<{W*{Y>  {r|   |   \\   \\ |         | |         | |         |{x\n{r'{Rv{r-{Rv{r'   '{Rv{r-{Rv{r' '{Rv{r-{Rv{r'     {Y''''{r '{Rv{r-{Rv{r'    '{Rv{r-{Rv{r''{Rv{r---{Rv{r---{Rv{r' '{Rv{r---{Rv{r---{Rv{r' '{Rv{r---{Rv{r---{Rv{r' {x\n\n\n                           jubelo@akriosmud.funcity.org\n                                 Jubelo & Belial",
    "json_class_name": "__Help__",
    "json_version": 1,
    "keywords": [
        "greet"
    ],
    "section": "player",
    "topics": "Informational",
    "viewable": "true"
}
